{
  "reqs": [
    {
      "name": "马克思主义",
      "num": "5"
    }
  ],
  "difficulty": null,
  "testName": "专项练习（马克思主义-53nwf1）",
  "model": [
    {
      "name": "马克思主义",
      "num": 5,
      "snum": 1,
      "enum": 5
    }
  ],
  "questions": [
    {
      "id": 20058,
      "titleHtml": "近年来，“元宇宙”已成为全球科技关注的焦点，正在为产业带来新变革，昭示着数字化未来的无限可能性。从哲学上看，下列关于“元宇宙”的说法不正确的是：",
      "type": "single",
      "globalAccuracy": 67,
      "correctAnswer": "3",
      "options": [
        {
          "label": "A",
          "value": "0",
          "text": "元宇宙是人的实践活动的产物"
        },
        {
          "label": "B",
          "value": "1",
          "text": "元宇宙是对物质世界的摹写和反映"
        },
        {
          "label": "C",
          "value": "2",
          "text": "元宇宙归根到底是现实世界的一种延伸和拓展"
        },
        {
          "label": "D",
          "value": "3",
          "text": "元宇宙本质上是从物质世界中独立出来的精神世界"
        }
      ],
      "analysisHtml": "A项正确，元宇宙是人类通过技术手段创造出来的虚拟空间，它是人类实践活动的产物。人们运用各种技术，如虚拟现实、增强现实、区块链等，来构建元宇宙，体现了人类的实践活动对其产生的作用。<br><br>B项正确，元宇宙中的各种元素、场景、规则等，都是对现实物质世界的摹写和反映。它可能会对现实世界的某些方面进行夸张、变形或重新组合，但本质上是基于现实世界的。<br><br>C项正确，元宇宙是利用数字技术将现实世界进行数字化拓展和延伸的虚拟空间，它在一定程度上反映了现实世界的特征和需求，是现实世界在数字领域的一种延伸和拓展。<br><br>D项错误，元宇宙并不是从物质世界中独立出来的精神世界。虽然它具有虚拟性，但它是建立在物质基础之上的，依赖于计算机硬件、网络基础设施等物质条件，并且其内容也是对物质世界的反映，不能脱离物质世界而独立存在。<br><br>本题为选非题，故正确答案为D。",
      "source": "2025年黑龙江公务员录用考试《行测》",
      "tag": "马克思主义",
      "materialHtml": "",
      "userAnswer": null,
      "memorize": false
    },
    {
      "id": 20462,
      "titleHtml": "守正创新深刻揭示了变与不变，继承与发展的辩证统一，下列与守正创新蕴含哲理相同的是：",
      "type": "single",
      "globalAccuracy": 75,
      "correctAnswer": "3",
      "options": [
        {
          "label": "A",
          "value": "0",
          "text": "旋岚偃岳而常静，江河竞注而不流"
        },
        {
          "label": "B",
          "value": "1",
          "text": "试玉要烧三日满，辨材须待七年期"
        },
        {
          "label": "C",
          "value": "2",
          "text": "却是平流无石处，时时闻说有沉沦"
        },
        {
          "label": "D",
          "value": "3",
          "text": "新竹高于旧竹枝，全凭老干为扶持"
        }
      ],
      "analysisHtml": "“守正”就是按照事物发展的客观规律来认识和改造世界；“创新”即人们充分发挥主观能动性，结合实际情况，有意识有目的地深化对客观世界的认识，积极主动地进行创造性活动。守正与创新是辩证统一的关系，体现了发展的观点。<br><br>A项错误，“旋岚偃岳而常静，江河竞注而不流”出自宋代释宗演的《颂古二十四首其一》，意思是可以吹倒山岳的暴风是静止的，江流河水滔滔不绝同时却是停滞不动的。这是用静止的观点看待事物，否认了绝对运动，属于形而上学的观点。<br><br>B项错误，“试玉要烧三日满，辨材须待七年期”出自唐代白居易的《放言五首·其三》，意思是检验玉真假还需要烧满三天，辨别木材还要等七年以后。这表明对人和事要得到全面的认识，都要经过时间的考验。体现的哲理是对复杂事物的认识要经历一个过程。<br><br>C项错误，“却是平流无石处，时时闻说有沉沦”出自唐代杜荀鹤的《泾溪》。意思是恰恰是在水流缓慢没有礁石的地方，却常常听到有人被淹死的消息。体现的哲理是矛盾双方在一定条件下可以相互转化。<br><br>D项正确，“新竹高于旧竹枝，全凭老干为扶持”出自清代郑板桥的《新竹》，意思是新长的竹子要比旧竹子高，它们的生长全凭老的枝干扶持。寓意着新事物具有强大的生命力，体现了发展的观点。唯物辩证法的发展观告诉我们要坚持与时俱进，培养创新精神，促进新事物的成长，使自己的思想符合变化了的客观实际。<br><br>故正确答案为D。",
      "source": "2025年山东公务员录用考试《行测》",
      "tag": "马克思主义",
      "materialHtml": "",
      "userAnswer": null,
      "memorize": false
    },
    {
      "id": 20463,
      "titleHtml": "打开窗户就有无人机把快递包裹送到家，上下班可以直接用手机打个“飞的”出门，每逢佳节可以预约定制个人专属的炫酷无人机灯光秀······千米以下的低空空域未来将充满无限可能。这表明：",
      "type": "single",
      "globalAccuracy": 65,
      "correctAnswer": "0",
      "options": [
        {
          "label": "A",
          "value": "0",
          "text": "科学技术是推动社会文明进步的重要力量"
        },
        {
          "label": "B",
          "value": "1",
          "text": "科学技术是推动社会历史发展的根本动力"
        },
        {
          "label": "C",
          "value": "2",
          "text": "科学技术是推动社会生存和发展的永恒条件"
        },
        {
          "label": "D",
          "value": "3",
          "text": "科学技术应用于生产过程的周期正日趋缩短"
        }
      ],
      "analysisHtml": "A项正确，科学技术是生产力的重要组成部分，属于智能性要素，科学技术应用于生产过程，与生产力中的劳动资料、劳动对象和劳动者等因素相结合而转化为实际的生产能力。科技进步通过推动生产力发展，进而推动生产关系变革，最终推动社会发展。题干通过“无人机送快递”“打‘飞的’”“定制灯光秀”等场景，展现了低空空域的科技应用对社会生活的影响，体现了科技作为生产力的关键要素，推动生产力发展，进而推动社会文明进步。<br><br>B项错误，马克思主义认为，社会历史发展的根本动力是社会基本矛盾，即“生产力与生产关系的矛盾、经济基础与上层建筑的矛盾”。而科学技术是社会发展的重要动力。每一次科学技术革命都会不同程度地引起生产方式、生活方式和思维方式的深刻变化和社会的巨大进步。<br><br>C项错误，马克思主义认为，自然地理环境是人类社会生存和发展永恒的、必要的条件，是人们生活和生产的自然基础。而科学技术是“历史范畴”，是人类社会发展到一定阶段的产物。没有科技，人类可通过简单生产方式生存；但没有物质生产，人类社会立即消亡。<br><br>D项错误，“科技应用周期缩短”指科技从研发成功到转化为现实生产力的时间越来越短，这一表述正确，但题干中只提到了“无人机技术已应用于生活场景”，没有涉及“无人机技术从研发到应用的周期”，与题干无关。<br><br>故正确答案为A。",
      "source": "2025年山东公务员录用考试《行测》",
      "tag": "马克思主义",
      "materialHtml": "",
      "userAnswer": null,
      "memorize": false
    },
    {
      "id": 24259,
      "titleHtml": "<p>我国沿海地区有大片的盐碱滩涂，过去由于无法种植粮食作物而长期抛荒。袁隆平院士等农业科学家艰苦科研攻关，成功培育并种植出了耐盐碱的“海水稻”。这说明：</p><p>①人定胜天，人类一定能战胜大自然</p><p>②物质决定意识，意识反作用于物质</p><p>③科学技术是第一生产力</p><p>④科技的进步速度取决于人的决心大小</p>",
      "type": "single",
      "globalAccuracy": 84,
      "correctAnswer": "1",
      "options": [
        {
          "label": "A",
          "value": "0",
          "text": "①④"
        },
        {
          "label": "B",
          "value": "1",
          "text": "②③"
        },
        {
          "label": "C",
          "value": "2",
          "text": "①③"
        },
        {
          "label": "D",
          "value": "3",
          "text": "②④"
        }
      ],
      "analysisHtml": "<p>①错误，②正确，辩证唯物主义中的唯物论指出，物质决定意识，意识反作用于物质。“人定胜天，人类一定能战胜大自然”的表述从哲学角度来看是过分夸大了主观能动性的主观唯心主义观点。而从题干中可以分析出，袁隆平院士等农业科学家所进行的艰苦科研攻关正是在发挥主观能动性的过程；培育并种植出了耐盐碱的“海水稻”，从而改变了人们对于盐碱地的利用，提高了粮食的产量，体现出意识对物质的反作用。</p><p>③正确，历史唯物主义指出，生产力主要有三个要素：劳动者、劳动工具和劳动对象。当科学技术被劳动者掌握，并且物化为劳动工具和劳动对象时，就成为了现实的生产力。邓小平曾提出过“科学技术是第一生产力”的论断。在1978年3月召开的全国科学大会开幕式上，邓小平指出：科学技术是生产力，这是马克思主义历来的观点。袁隆平院士等农业科学家艰苦科研攻关，成功培育并种植出了耐盐碱的“海水稻”，体现了“科学技术是第一生产力”的论断。</p><p>④错误，科技的进步速度与多种因素有关，政治因素、经济发展水平、文化因素等都能对科技发展产生一定的影响，但“取决于人的决心大小”是过分夸大了主观能动性的主观唯心主义观点。</p><p>综上所述，正确的是②③。</p><p>故正确答案为B。</p>",
      "source": "2023年北京市公务员录用考试《行测》",
      "tag": "马克思主义",
      "materialHtml": "",
      "userAnswer": null,
      "memorize": false
    },
    {
      "id": 26187,
      "titleHtml": "<p>近年来，青海海南州在荒漠化土地上发展清洁能源，建设大量光伏板利用太阳能资源，同时创新发展“板下经济”，在光伏板下发展畜牧业，探索出“牧光互补”模式，为青海高原乃至世界同类地区提供了可持续发展的有益借鉴。上述材料启示我们（    ）。</p>",
      "type": "single",
      "globalAccuracy": 72,
      "correctAnswer": "1",
      "options": [
        {
          "label": "A",
          "value": "0",
          "text": "自然界的存在和发展是客观的，具有物质性"
        },
        {
          "label": "B",
          "value": "1",
          "text": "要把握事物的固有联系，建立新的联系"
        },
        {
          "label": "C",
          "value": "2",
          "text": "科技进步使物质世界变化依赖于人的意识"
        },
        {
          "label": "D",
          "value": "3",
          "text": "人们能够在一定程度上改变并利用自然规律"
        }
      ],
      "analysisHtml": "<p>本题考查马克思主义。</p><p>A项错误，物质是不依赖于人类的意识而存在，并能为人类的意识所反映的客观实在。自然界具有物质性，其存在发展是客观的。题干重点不是强调自然界本身的客观性，而是强调人如何利用客观条件建立新联系，故该选项与题干启示不符。</p><p>B项正确，联系是指事物之间以及事物内部诸要素之间的相互影响、相互作用和相互制约。联系的客观性是指事物之间的相互联系是事物本身所固有的，是不以人的意志为转移的，不能用主观臆造的联系代替客观的、真实的联系。但人可以把握事物的固有联系，根据事物的固有属性建立新的具体联系。海南州抓住荒漠化土地、太阳能、畜牧业的固有条件，创新“牧光互补”模式，正是这一原理的典型应用。</p><p>C项错误，物质决定意识，意识是客观存在在人脑中的映象。科技进步只是人认识和改造世界的手段，不会使物质世界的变化依赖于人的意识，故该选项违背唯物主义基本原理。</p><p>D项错误，规律具有客观性，规律是运动着的事物本身所固有的，是不以任何人的意志为转移的。人们不能任意地创造或消灭规律，也不能任意地改变规律，故该选项“改变自然规律”的表述错误。</p><p>故正确答案为B。</p>",
      "source": "2026年上海公务员录用考试《行测》",
      "tag": "马克思主义",
      "materialHtml": "",
      "userAnswer": null,
      "memorize": false
    }
  ]
}
